
{
    "scenarios":[
        {
            "probability":0.01,
            "index":72,
            "scenario_builder_factory":"gov.lanl.micot.application.scenariobuilder.UniformEdgeDamageScenarioConfigurationBuilder",
            "modifications":[
                {
                    "component_type":"gov.lanl.micot.infrastructure.ep.model.LineImpl",
                    "id":[
                        {
                            "id_key":"OPENDSS_LEGACY_ID",
                            "id_value":"l115",
                            "id_type":"string"
                        }
                    ],
                    "modification":[
                        {
                            "modification_key":"DISABLED",
                            "modification_value":false,
                            "modification_type":"boolean"
                        }
                    ]
                },
                {
                    "component_type":"gov.lanl.micot.infrastructure.ep.model.LineImpl",
                    "id":[
                        {
                            "id_key":"OPENDSS_LEGACY_ID",
                            "id_value":"l1",
                            "id_type":"string"
                        }
                    ],
                    "modification":[
                        {
                            "modification_key":"DISABLED",
                            "modification_value":false,
                            "modification_type":"boolean"
                        }
                    ]
                },
                {
                    "component_type":"gov.lanl.micot.infrastructure.ep.model.LineImpl",
                    "id":[
                        {
                            "id_key":"OPENDSS_LEGACY_ID",
                            "id_value":"l2",
                            "id_type":"string"
                        }
                    ],
                    "modification":[
                        {
                            "modification_key":"DISABLED",
                            "modification_value":false,
                            "modification_type":"boolean"
                        }
                    ]
                },
                {
                    "component_type":"gov.lanl.micot.infrastructure.ep.model.LineImpl",
                    "id":[
                        {
                            "id_key":"OPENDSS_LEGACY_ID",
                            "id_value":"l3",
                            "id_type":"string"
                        }
                    ],
                    "modification":[
                        {
                            "modification_key":"DISABLED",
                            "modification_value":false,
                            "modification_type":"boolean"
                        }
                    ]
                },
                {
                    "component_type":"gov.lanl.micot.infrastructure.ep.model.LineImpl",
                    "id":[
                        {
                            "id_key":"OPENDSS_LEGACY_ID",
                            "id_value":"l4",
                            "id_type":"string"
                        }
                    ],
                    "modification":[
                        {
                            "modification_key":"DISABLED",
                            "modification_value":false,
                            "modification_type":"boolean"
                        }
                    ]
                },
                {
                    "component_type":"gov.lanl.micot.infrastructure.ep.model.LineImpl",
                    "id":[
                        {
                            "id_key":"OPENDSS_LEGACY_ID",
                            "id_value":"l5",
                            "id_type":"string"
                        }
                    ],
                    "modification":[
                        {
                            "modification_key":"DISABLED",
                            "modification_value":false,
                            "modification_type":"boolean"
                        }
                    ]
                },
                {
                    "component_type":"gov.lanl.micot.infrastructure.ep.model.LineImpl",
                    "id":[
                        {
                            "id_key":"OPENDSS_LEGACY_ID",
                            "id_value":"l6",
                            "id_type":"string"
                        }
                    ],
                    "modification":[
                        {
                            "modification_key":"DISABLED",
                            "modification_value":false,
                            "modification_type":"boolean"
                        }
                    ]
                },
                {
                    "component_type":"gov.lanl.micot.infrastructure.ep.model.LineImpl",
                    "id":[
                        {
                            "id_key":"OPENDSS_LEGACY_ID",
                            "id_value":"l7",
                            "id_type":"string"
                        }
                    ],
                    "modification":[
                        {
                            "modification_key":"DISABLED",
                            "modification_value":false,
                            "modification_type":"boolean"
                        }
                    ]
                },
                {
                    "component_type":"gov.lanl.micot.infrastructure.ep.model.LineImpl",
                    "id":[
                        {
                            "id_key":"OPENDSS_LEGACY_ID",
                            "id_value":"l8",
                            "id_type":"string"
                        }
                    ],
                    "modification":[
                        {
                            "modification_key":"DISABLED",
                            "modification_value":false,
                            "modification_type":"boolean"
                        }
                    ]
                },
                {
                    "component_type":"gov.lanl.micot.infrastructure.ep.model.LineImpl",
                    "id":[
                        {
                            "id_key":"OPENDSS_LEGACY_ID",
                            "id_value":"l9",
                            "id_type":"string"
                        }
                    ],
                    "modification":[
                        {
                            "modification_key":"DISABLED",
                            "modification_value":false,
                            "modification_type":"boolean"
                        }
                    ]
                },
                {
                    "component_type":"gov.lanl.micot.infrastructure.ep.model.LineImpl",
                    "id":[
                        {
                            "id_key":"OPENDSS_LEGACY_ID",
                            "id_value":"l10",
                            "id_type":"string"
                        }
                    ],
                    "modification":[
                        {
                            "modification_key":"DISABLED",
                            "modification_value":false,
                            "modification_type":"boolean"
                        }
                    ]
                },
                {
                    "component_type":"gov.lanl.micot.infrastructure.ep.model.LineImpl",
                    "id":[
                        {
                            "id_key":"OPENDSS_LEGACY_ID",
                            "id_value":"l11",
                            "id_type":"string"
                        }
                    ],
                    "modification":[
                        {
                            "modification_key":"DISABLED",
                            "modification_value":false,
                            "modification_type":"boolean"
                        }
                    ]
                },
                {
                    "component_type":"gov.lanl.micot.infrastructure.ep.model.LineImpl",
                    "id":[
                        {
                            "id_key":"OPENDSS_LEGACY_ID",
                            "id_value":"l12",
                            "id_type":"string"
                        }
                    ],
                    "modification":[
                        {
                            "modification_key":"DISABLED",
                            "modification_value":false,
                            "modification_type":"boolean"
                        }
                    ]
                },
                {
                    "component_type":"gov.lanl.micot.infrastructure.ep.model.LineImpl",
                    "id":[
                        {
                            "id_key":"OPENDSS_LEGACY_ID",
                            "id_value":"l13",
                            "id_type":"string"
                        }
                    ],
                    "modification":[
                        {
                            "modification_key":"DISABLED",
                            "modification_value":false,
                            "modification_type":"boolean"
                        }
                    ]
                },
                {
                    "component_type":"gov.lanl.micot.infrastructure.ep.model.LineImpl",
                    "id":[
                        {
                            "id_key":"OPENDSS_LEGACY_ID",
                            "id_value":"l14",
                            "id_type":"string"
                        }
                    ],
                    "modification":[
                        {
                            "modification_key":"DISABLED",
                            "modification_value":false,
                            "modification_type":"boolean"
                        }
                    ]
                },
                {
                    "component_type":"gov.lanl.micot.infrastructure.ep.model.LineImpl",
                    "id":[
                        {
                            "id_key":"OPENDSS_LEGACY_ID",
                            "id_value":"l15",
                            "id_type":"string"
                        }
                    ],
                    "modification":[
                        {
                            "modification_key":"DISABLED",
                            "modification_value":false,
                            "modification_type":"boolean"
                        }
                    ]
                },
                {
                    "component_type":"gov.lanl.micot.infrastructure.ep.model.LineImpl",
                    "id":[
                        {
                            "id_key":"OPENDSS_LEGACY_ID",
                            "id_value":"l16",
                            "id_type":"string"
                        }
                    ],
                    "modification":[
                        {
                            "modification_key":"DISABLED",
                            "modification_value":false,
                            "modification_type":"boolean"
                        }
                    ]
                },
                {
                    "component_type":"gov.lanl.micot.infrastructure.ep.model.LineImpl",
                    "id":[
                        {
                            "id_key":"OPENDSS_LEGACY_ID",
                            "id_value":"l17",
                            "id_type":"string"
                        }
                    ],
                    "modification":[
                        {
                            "modification_key":"DISABLED",
                            "modification_value":false,
                            "modification_type":"boolean"
                        }
                    ]
                },
                {
                    "component_type":"gov.lanl.micot.infrastructure.ep.model.LineImpl",
                    "id":[
                        {
                            "id_key":"OPENDSS_LEGACY_ID",
                            "id_value":"l18",
                            "id_type":"string"
                        }
                    ],
                    "modification":[
                        {
                            "modification_key":"DISABLED",
                            "modification_value":false,
                            "modification_type":"boolean"
                        }
                    ]
                },
                {
                    "component_type":"gov.lanl.micot.infrastructure.ep.model.LineImpl",
                    "id":[
                        {
                            "id_key":"OPENDSS_LEGACY_ID",
                            "id_value":"l19",
                            "id_type":"string"
                        }
                    ],
                    "modification":[
                        {
                            "modification_key":"DISABLED",
                            "modification_value":false,
                            "modification_type":"boolean"
                        }
                    ]
                },
                {
                    "component_type":"gov.lanl.micot.infrastructure.ep.model.LineImpl",
                    "id":[
                        {
                            "id_key":"OPENDSS_LEGACY_ID",
                            "id_value":"l20",
                            "id_type":"string"
                        }
                    ],
                    "modification":[
                        {
                            "modification_key":"DISABLED",
                            "modification_value":false,
                            "modification_type":"boolean"
                        }
                    ]
                },
                {
                    "component_type":"gov.lanl.micot.infrastructure.ep.model.LineImpl",
                    "id":[
                        {
                            "id_key":"OPENDSS_LEGACY_ID",
                            "id_value":"l21",
                            "id_type":"string"
                        }
                    ],
                    "modification":[
                        {
                            "modification_key":"DISABLED",
                            "modification_value":false,
                            "modification_type":"boolean"
                        }
                    ]
                },
                {
                    "component_type":"gov.lanl.micot.infrastructure.ep.model.LineImpl",
                    "id":[
                        {
                            "id_key":"OPENDSS_LEGACY_ID",
                            "id_value":"l22",
                            "id_type":"string"
                        }
                    ],
                    "modification":[
                        {
                            "modification_key":"DISABLED",
                            "modification_value":false,
                            "modification_type":"boolean"
                        }
                    ]
                },
                {
                    "component_type":"gov.lanl.micot.infrastructure.ep.model.LineImpl",
                    "id":[
                        {
                            "id_key":"OPENDSS_LEGACY_ID",
                            "id_value":"l23",
                            "id_type":"string"
                        }
                    ],
                    "modification":[
                        {
                            "modification_key":"DISABLED",
                            "modification_value":false,
                            "modification_type":"boolean"
                        }
                    ]
                },
                {
                    "component_type":"gov.lanl.micot.infrastructure.ep.model.LineImpl",
                    "id":[
                        {
                            "id_key":"OPENDSS_LEGACY_ID",
                            "id_value":"l24",
                            "id_type":"string"
                        }
                    ],
                    "modification":[
                        {
                            "modification_key":"DISABLED",
                            "modification_value":false,
                            "modification_type":"boolean"
                        }
                    ]
                },
                {
                    "component_type":"gov.lanl.micot.infrastructure.ep.model.LineImpl",
                    "id":[
                        {
                            "id_key":"OPENDSS_LEGACY_ID",
                            "id_value":"l25",
                            "id_type":"string"
                        }
                    ],
                    "modification":[
                        {
                            "modification_key":"DISABLED",
                            "modification_value":false,
                            "modification_type":"boolean"
                        }
                    ]
                },
                {
                    "component_type":"gov.lanl.micot.infrastructure.ep.model.LineImpl",
                    "id":[
                        {
                            "id_key":"OPENDSS_LEGACY_ID",
                            "id_value":"l26",
                            "id_type":"string"
                        }
                    ],
                    "modification":[
                        {
                            "modification_key":"DISABLED",
                            "modification_value":false,
                            "modification_type":"boolean"
                        }
                    ]
                },
                {
                    "component_type":"gov.lanl.micot.infrastructure.ep.model.LineImpl",
                    "id":[
                        {
                            "id_key":"OPENDSS_LEGACY_ID",
                            "id_value":"l27",
                            "id_type":"string"
                        }
                    ],
                    "modification":[
                        {
                            "modification_key":"DISABLED",
                            "modification_value":false,
                            "modification_type":"boolean"
                        }
                    ]
                },
                {
                    "component_type":"gov.lanl.micot.infrastructure.ep.model.LineImpl",
                    "id":[
                        {
                            "id_key":"OPENDSS_LEGACY_ID",
                            "id_value":"l28",
                            "id_type":"string"
                        }
                    ],
                    "modification":[
                        {
                            "modification_key":"DISABLED",
                            "modification_value":false,
                            "modification_type":"boolean"
                        }
                    ]
                },
                {
                    "component_type":"gov.lanl.micot.infrastructure.ep.model.LineImpl",
                    "id":[
                        {
                            "id_key":"OPENDSS_LEGACY_ID",
                            "id_value":"l29",
                            "id_type":"string"
                        }
                    ],
                    "modification":[
                        {
                            "modification_key":"DISABLED",
                            "modification_value":true,
                            "modification_type":"boolean"
                        }
                    ]
                },
                {
                    "component_type":"gov.lanl.micot.infrastructure.ep.model.LineImpl",
                    "id":[
                        {
                            "id_key":"OPENDSS_LEGACY_ID",
                            "id_value":"l30",
                            "id_type":"string"
                        }
                    ],
                    "modification":[
                        {
                            "modification_key":"DISABLED",
                            "modification_value":false,
                            "modification_type":"boolean"
                        }
                    ]
                },
                {
                    "component_type":"gov.lanl.micot.infrastructure.ep.model.LineImpl",
                    "id":[
                        {
                            "id_key":"OPENDSS_LEGACY_ID",
                            "id_value":"l31",
                            "id_type":"string"
                        }
                    ],
                    "modification":[
                        {
                            "modification_key":"DISABLED",
                            "modification_value":false,
                            "modification_type":"boolean"
                        }
                    ]
                },
                {
                    "component_type":"gov.lanl.micot.infrastructure.ep.model.LineImpl",
                    "id":[
                        {
                            "id_key":"OPENDSS_LEGACY_ID",
                            "id_value":"l32",
                            "id_type":"string"
                        }
                    ],
                    "modification":[
                        {
                            "modification_key":"DISABLED",
                            "modification_value":false,
                            "modification_type":"boolean"
                        }
                    ]
                },
                {
                    "component_type":"gov.lanl.micot.infrastructure.ep.model.LineImpl",
                    "id":[
                        {
                            "id_key":"OPENDSS_LEGACY_ID",
                            "id_value":"l33",
                            "id_type":"string"
                        }
                    ],
                    "modification":[
                        {
                            "modification_key":"DISABLED",
                            "modification_value":false,
                            "modification_type":"boolean"
                        }
                    ]
                },
                {
                    "component_type":"gov.lanl.micot.infrastructure.ep.model.LineImpl",
                    "id":[
                        {
                            "id_key":"OPENDSS_LEGACY_ID",
                            "id_value":"l34",
                            "id_type":"string"
                        }
                    ],
                    "modification":[
                        {
                            "modification_key":"DISABLED",
                            "modification_value":false,
                            "modification_type":"boolean"
                        }
                    ]
                },
                {
                    "component_type":"gov.lanl.micot.infrastructure.ep.model.LineImpl",
                    "id":[
                        {
                            "id_key":"OPENDSS_LEGACY_ID",
                            "id_value":"l35",
                            "id_type":"string"
                        }
                    ],
                    "modification":[
                        {
                            "modification_key":"DISABLED",
                            "modification_value":false,
                            "modification_type":"boolean"
                        }
                    ]
                },
                {
                    "component_type":"gov.lanl.micot.infrastructure.ep.model.LineImpl",
                    "id":[
                        {
                            "id_key":"OPENDSS_LEGACY_ID",
                            "id_value":"l36",
                            "id_type":"string"
                        }
                    ],
                    "modification":[
                        {
                            "modification_key":"DISABLED",
                            "modification_value":false,
                            "modification_type":"boolean"
                        }
                    ]
                },
                {
                    "component_type":"gov.lanl.micot.infrastructure.ep.model.LineImpl",
                    "id":[
                        {
                            "id_key":"OPENDSS_LEGACY_ID",
                            "id_value":"l37",
                            "id_type":"string"
                        }
                    ],
                    "modification":[
                        {
                            "modification_key":"DISABLED",
                            "modification_value":false,
                            "modification_type":"boolean"
                        }
                    ]
                },
                {
                    "component_type":"gov.lanl.micot.infrastructure.ep.model.LineImpl",
                    "id":[
                        {
                            "id_key":"OPENDSS_LEGACY_ID",
                            "id_value":"l38",
                            "id_type":"string"
                        }
                    ],
                    "modification":[
                        {
                            "modification_key":"DISABLED",
                            "modification_value":false,
                            "modification_type":"boolean"
                        }
                    ]
                },
                {
                    "component_type":"gov.lanl.micot.infrastructure.ep.model.LineImpl",
                    "id":[
                        {
                            "id_key":"OPENDSS_LEGACY_ID",
                            "id_value":"l39",
                            "id_type":"string"
                        }
                    ],
                    "modification":[
                        {
                            "modification_key":"DISABLED",
                            "modification_value":false,
                            "modification_type":"boolean"
                        }
                    ]
                },
                {
                    "component_type":"gov.lanl.micot.infrastructure.ep.model.LineImpl",
                    "id":[
                        {
                            "id_key":"OPENDSS_LEGACY_ID",
                            "id_value":"l40",
                            "id_type":"string"
                        }
                    ],
                    "modification":[
                        {
                            "modification_key":"DISABLED",
                            "modification_value":false,
                            "modification_type":"boolean"
                        }
                    ]
                },
                {
                    "component_type":"gov.lanl.micot.infrastructure.ep.model.LineImpl",
                    "id":[
                        {
                            "id_key":"OPENDSS_LEGACY_ID",
                            "id_value":"l41",
                            "id_type":"string"
                        }
                    ],
                    "modification":[
                        {
                            "modification_key":"DISABLED",
                            "modification_value":false,
                            "modification_type":"boolean"
                        }
                    ]
                },
                {
                    "component_type":"gov.lanl.micot.infrastructure.ep.model.LineImpl",
                    "id":[
                        {
                            "id_key":"OPENDSS_LEGACY_ID",
                            "id_value":"l42",
                            "id_type":"string"
                        }
                    ],
                    "modification":[
                        {
                            "modification_key":"DISABLED",
                            "modification_value":false,
                            "modification_type":"boolean"
                        }
                    ]
                },
                {
                    "component_type":"gov.lanl.micot.infrastructure.ep.model.LineImpl",
                    "id":[
                        {
                            "id_key":"OPENDSS_LEGACY_ID",
                            "id_value":"l44",
                            "id_type":"string"
                        }
                    ],
                    "modification":[
                        {
                            "modification_key":"DISABLED",
                            "modification_value":false,
                            "modification_type":"boolean"
                        }
                    ]
                },
                {
                    "component_type":"gov.lanl.micot.infrastructure.ep.model.LineImpl",
                    "id":[
                        {
                            "id_key":"OPENDSS_LEGACY_ID",
                            "id_value":"l45",
                            "id_type":"string"
                        }
                    ],
                    "modification":[
                        {
                            "modification_key":"DISABLED",
                            "modification_value":false,
                            "modification_type":"boolean"
                        }
                    ]
                },
                {
                    "component_type":"gov.lanl.micot.infrastructure.ep.model.LineImpl",
                    "id":[
                        {
                            "id_key":"OPENDSS_LEGACY_ID",
                            "id_value":"l46",
                            "id_type":"string"
                        }
                    ],
                    "modification":[
                        {
                            "modification_key":"DISABLED",
                            "modification_value":false,
                            "modification_type":"boolean"
                        }
                    ]
                },
                {
                    "component_type":"gov.lanl.micot.infrastructure.ep.model.LineImpl",
                    "id":[
                        {
                            "id_key":"OPENDSS_LEGACY_ID",
                            "id_value":"l47",
                            "id_type":"string"
                        }
                    ],
                    "modification":[
                        {
                            "modification_key":"DISABLED",
                            "modification_value":false,
                            "modification_type":"boolean"
                        }
                    ]
                },
                {
                    "component_type":"gov.lanl.micot.infrastructure.ep.model.LineImpl",
                    "id":[
                        {
                            "id_key":"OPENDSS_LEGACY_ID",
                            "id_value":"l48",
                            "id_type":"string"
                        }
                    ],
                    "modification":[
                        {
                            "modification_key":"DISABLED",
                            "modification_value":false,
                            "modification_type":"boolean"
                        }
                    ]
                },
                {
                    "component_type":"gov.lanl.micot.infrastructure.ep.model.LineImpl",
                    "id":[
                        {
                            "id_key":"OPENDSS_LEGACY_ID",
                            "id_value":"l49",
                            "id_type":"string"
                        }
                    ],
                    "modification":[
                        {
                            "modification_key":"DISABLED",
                            "modification_value":false,
                            "modification_type":"boolean"
                        }
                    ]
                },
                {
                    "component_type":"gov.lanl.micot.infrastructure.ep.model.LineImpl",
                    "id":[
                        {
                            "id_key":"OPENDSS_LEGACY_ID",
                            "id_value":"l50",
                            "id_type":"string"
                        }
                    ],
                    "modification":[
                        {
                            "modification_key":"DISABLED",
                            "modification_value":false,
                            "modification_type":"boolean"
                        }
                    ]
                },
                {
                    "component_type":"gov.lanl.micot.infrastructure.ep.model.LineImpl",
                    "id":[
                        {
                            "id_key":"OPENDSS_LEGACY_ID",
                            "id_value":"l51",
                            "id_type":"string"
                        }
                    ],
                    "modification":[
                        {
                            "modification_key":"DISABLED",
                            "modification_value":false,
                            "modification_type":"boolean"
                        }
                    ]
                },
                {
                    "component_type":"gov.lanl.micot.infrastructure.ep.model.LineImpl",
                    "id":[
                        {
                            "id_key":"OPENDSS_LEGACY_ID",
                            "id_value":"l52",
                            "id_type":"string"
                        }
                    ],
                    "modification":[
                        {
                            "modification_key":"DISABLED",
                            "modification_value":false,
                            "modification_type":"boolean"
                        }
                    ]
                },
                {
                    "component_type":"gov.lanl.micot.infrastructure.ep.model.LineImpl",
                    "id":[
                        {
                            "id_key":"OPENDSS_LEGACY_ID",
                            "id_value":"l53",
                            "id_type":"string"
                        }
                    ],
                    "modification":[
                        {
                            "modification_key":"DISABLED",
                            "modification_value":false,
                            "modification_type":"boolean"
                        }
                    ]
                },
                {
                    "component_type":"gov.lanl.micot.infrastructure.ep.model.LineImpl",
                    "id":[
                        {
                            "id_key":"OPENDSS_LEGACY_ID",
                            "id_value":"l54",
                            "id_type":"string"
                        }
                    ],
                    "modification":[
                        {
                            "modification_key":"DISABLED",
                            "modification_value":false,
                            "modification_type":"boolean"
                        }
                    ]
                },
                {
                    "component_type":"gov.lanl.micot.infrastructure.ep.model.LineImpl",
                    "id":[
                        {
                            "id_key":"OPENDSS_LEGACY_ID",
                            "id_value":"l55",
                            "id_type":"string"
                        }
                    ],
                    "modification":[
                        {
                            "modification_key":"DISABLED",
                            "modification_value":false,
                            "modification_type":"boolean"
                        }
                    ]
                },
                {
                    "component_type":"gov.lanl.micot.infrastructure.ep.model.LineImpl",
                    "id":[
                        {
                            "id_key":"OPENDSS_LEGACY_ID",
                            "id_value":"l56",
                            "id_type":"string"
                        }
                    ],
                    "modification":[
                        {
                            "modification_key":"DISABLED",
                            "modification_value":false,
                            "modification_type":"boolean"
                        }
                    ]
                },
                {
                    "component_type":"gov.lanl.micot.infrastructure.ep.model.LineImpl",
                    "id":[
                        {
                            "id_key":"OPENDSS_LEGACY_ID",
                            "id_value":"l57",
                            "id_type":"string"
                        }
                    ],
                    "modification":[
                        {
                            "modification_key":"DISABLED",
                            "modification_value":false,
                            "modification_type":"boolean"
                        }
                    ]
                },
                {
                    "component_type":"gov.lanl.micot.infrastructure.ep.model.LineImpl",
                    "id":[
                        {
                            "id_key":"OPENDSS_LEGACY_ID",
                            "id_value":"l58",
                            "id_type":"string"
                        }
                    ],
                    "modification":[
                        {
                            "modification_key":"DISABLED",
                            "modification_value":false,
                            "modification_type":"boolean"
                        }
                    ]
                },
                {
                    "component_type":"gov.lanl.micot.infrastructure.ep.model.LineImpl",
                    "id":[
                        {
                            "id_key":"OPENDSS_LEGACY_ID",
                            "id_value":"l59",
                            "id_type":"string"
                        }
                    ],
                    "modification":[
                        {
                            "modification_key":"DISABLED",
                            "modification_value":false,
                            "modification_type":"boolean"
                        }
                    ]
                },
                {
                    "component_type":"gov.lanl.micot.infrastructure.ep.model.LineImpl",
                    "id":[
                        {
                            "id_key":"OPENDSS_LEGACY_ID",
                            "id_value":"l60",
                            "id_type":"string"
                        }
                    ],
                    "modification":[
                        {
                            "modification_key":"DISABLED",
                            "modification_value":false,
                            "modification_type":"boolean"
                        }
                    ]
                },
                {
                    "component_type":"gov.lanl.micot.infrastructure.ep.model.LineImpl",
                    "id":[
                        {
                            "id_key":"OPENDSS_LEGACY_ID",
                            "id_value":"l66",
                            "id_type":"string"
                        }
                    ],
                    "modification":[
                        {
                            "modification_key":"DISABLED",
                            "modification_value":false,
                            "modification_type":"boolean"
                        }
                    ]
                },
                {
                    "component_type":"gov.lanl.micot.infrastructure.ep.model.LineImpl",
                    "id":[
                        {
                            "id_key":"OPENDSS_LEGACY_ID",
                            "id_value":"l67",
                            "id_type":"string"
                        }
                    ],
                    "modification":[
                        {
                            "modification_key":"DISABLED",
                            "modification_value":false,
                            "modification_type":"boolean"
                        }
                    ]
                },
                {
                    "component_type":"gov.lanl.micot.infrastructure.ep.model.LineImpl",
                    "id":[
                        {
                            "id_key":"OPENDSS_LEGACY_ID",
                            "id_value":"l68",
                            "id_type":"string"
                        }
                    ],
                    "modification":[
                        {
                            "modification_key":"DISABLED",
                            "modification_value":false,
                            "modification_type":"boolean"
                        }
                    ]
                },
                {
                    "component_type":"gov.lanl.micot.infrastructure.ep.model.LineImpl",
                    "id":[
                        {
                            "id_key":"OPENDSS_LEGACY_ID",
                            "id_value":"l69",
                            "id_type":"string"
                        }
                    ],
                    "modification":[
                        {
                            "modification_key":"DISABLED",
                            "modification_value":false,
                            "modification_type":"boolean"
                        }
                    ]
                },
                {
                    "component_type":"gov.lanl.micot.infrastructure.ep.model.LineImpl",
                    "id":[
                        {
                            "id_key":"OPENDSS_LEGACY_ID",
                            "id_value":"l70",
                            "id_type":"string"
                        }
                    ],
                    "modification":[
                        {
                            "modification_key":"DISABLED",
                            "modification_value":false,
                            "modification_type":"boolean"
                        }
                    ]
                },
                {
                    "component_type":"gov.lanl.micot.infrastructure.ep.model.LineImpl",
                    "id":[
                        {
                            "id_key":"OPENDSS_LEGACY_ID",
                            "id_value":"l71",
                            "id_type":"string"
                        }
                    ],
                    "modification":[
                        {
                            "modification_key":"DISABLED",
                            "modification_value":false,
                            "modification_type":"boolean"
                        }
                    ]
                },
                {
                    "component_type":"gov.lanl.micot.infrastructure.ep.model.LineImpl",
                    "id":[
                        {
                            "id_key":"OPENDSS_LEGACY_ID",
                            "id_value":"l72",
                            "id_type":"string"
                        }
                    ],
                    "modification":[
                        {
                            "modification_key":"DISABLED",
                            "modification_value":false,
                            "modification_type":"boolean"
                        }
                    ]
                },
                {
                    "component_type":"gov.lanl.micot.infrastructure.ep.model.LineImpl",
                    "id":[
                        {
                            "id_key":"OPENDSS_LEGACY_ID",
                            "id_value":"l73",
                            "id_type":"string"
                        }
                    ],
                    "modification":[
                        {
                            "modification_key":"DISABLED",
                            "modification_value":false,
                            "modification_type":"boolean"
                        }
                    ]
                },
                {
                    "component_type":"gov.lanl.micot.infrastructure.ep.model.LineImpl",
                    "id":[
                        {
                            "id_key":"OPENDSS_LEGACY_ID",
                            "id_value":"l74",
                            "id_type":"string"
                        }
                    ],
                    "modification":[
                        {
                            "modification_key":"DISABLED",
                            "modification_value":false,
                            "modification_type":"boolean"
                        }
                    ]
                },
                {
                    "component_type":"gov.lanl.micot.infrastructure.ep.model.LineImpl",
                    "id":[
                        {
                            "id_key":"OPENDSS_LEGACY_ID",
                            "id_value":"l75",
                            "id_type":"string"
                        }
                    ],
                    "modification":[
                        {
                            "modification_key":"DISABLED",
                            "modification_value":false,
                            "modification_type":"boolean"
                        }
                    ]
                },
                {
                    "component_type":"gov.lanl.micot.infrastructure.ep.model.LineImpl",
                    "id":[
                        {
                            "id_key":"OPENDSS_LEGACY_ID",
                            "id_value":"l76",
                            "id_type":"string"
                        }
                    ],
                    "modification":[
                        {
                            "modification_key":"DISABLED",
                            "modification_value":false,
                            "modification_type":"boolean"
                        }
                    ]
                },
                {
                    "component_type":"gov.lanl.micot.infrastructure.ep.model.LineImpl",
                    "id":[
                        {
                            "id_key":"OPENDSS_LEGACY_ID",
                            "id_value":"l77",
                            "id_type":"string"
                        }
                    ],
                    "modification":[
                        {
                            "modification_key":"DISABLED",
                            "modification_value":false,
                            "modification_type":"boolean"
                        }
                    ]
                },
                {
                    "component_type":"gov.lanl.micot.infrastructure.ep.model.LineImpl",
                    "id":[
                        {
                            "id_key":"OPENDSS_LEGACY_ID",
                            "id_value":"l78",
                            "id_type":"string"
                        }
                    ],
                    "modification":[
                        {
                            "modification_key":"DISABLED",
                            "modification_value":false,
                            "modification_type":"boolean"
                        }
                    ]
                },
                {
                    "component_type":"gov.lanl.micot.infrastructure.ep.model.LineImpl",
                    "id":[
                        {
                            "id_key":"OPENDSS_LEGACY_ID",
                            "id_value":"l79",
                            "id_type":"string"
                        }
                    ],
                    "modification":[
                        {
                            "modification_key":"DISABLED",
                            "modification_value":false,
                            "modification_type":"boolean"
                        }
                    ]
                },
                {
                    "component_type":"gov.lanl.micot.infrastructure.ep.model.LineImpl",
                    "id":[
                        {
                            "id_key":"OPENDSS_LEGACY_ID",
                            "id_value":"l80",
                            "id_type":"string"
                        }
                    ],
                    "modification":[
                        {
                            "modification_key":"DISABLED",
                            "modification_value":false,
                            "modification_type":"boolean"
                        }
                    ]
                },
                {
                    "component_type":"gov.lanl.micot.infrastructure.ep.model.LineImpl",
                    "id":[
                        {
                            "id_key":"OPENDSS_LEGACY_ID",
                            "id_value":"l81",
                            "id_type":"string"
                        }
                    ],
                    "modification":[
                        {
                            "modification_key":"DISABLED",
                            "modification_value":false,
                            "modification_type":"boolean"
                        }
                    ]
                },
                {
                    "component_type":"gov.lanl.micot.infrastructure.ep.model.LineImpl",
                    "id":[
                        {
                            "id_key":"OPENDSS_LEGACY_ID",
                            "id_value":"l82",
                            "id_type":"string"
                        }
                    ],
                    "modification":[
                        {
                            "modification_key":"DISABLED",
                            "modification_value":false,
                            "modification_type":"boolean"
                        }
                    ]
                },
                {
                    "component_type":"gov.lanl.micot.infrastructure.ep.model.LineImpl",
                    "id":[
                        {
                            "id_key":"OPENDSS_LEGACY_ID",
                            "id_value":"l83",
                            "id_type":"string"
                        }
                    ],
                    "modification":[
                        {
                            "modification_key":"DISABLED",
                            "modification_value":false,
                            "modification_type":"boolean"
                        }
                    ]
                },
                {
                    "component_type":"gov.lanl.micot.infrastructure.ep.model.LineImpl",
                    "id":[
                        {
                            "id_key":"OPENDSS_LEGACY_ID",
                            "id_value":"l84",
                            "id_type":"string"
                        }
                    ],
                    "modification":[
                        {
                            "modification_key":"DISABLED",
                            "modification_value":false,
                            "modification_type":"boolean"
                        }
                    ]
                },
                {
                    "component_type":"gov.lanl.micot.infrastructure.ep.model.LineImpl",
                    "id":[
                        {
                            "id_key":"OPENDSS_LEGACY_ID",
                            "id_value":"l85",
                            "id_type":"string"
                        }
                    ],
                    "modification":[
                        {
                            "modification_key":"DISABLED",
                            "modification_value":false,
                            "modification_type":"boolean"
                        }
                    ]
                },
                {
                    "component_type":"gov.lanl.micot.infrastructure.ep.model.LineImpl",
                    "id":[
                        {
                            "id_key":"OPENDSS_LEGACY_ID",
                            "id_value":"l86",
                            "id_type":"string"
                        }
                    ],
                    "modification":[
                        {
                            "modification_key":"DISABLED",
                            "modification_value":false,
                            "modification_type":"boolean"
                        }
                    ]
                },
                {
                    "component_type":"gov.lanl.micot.infrastructure.ep.model.LineImpl",
                    "id":[
                        {
                            "id_key":"OPENDSS_LEGACY_ID",
                            "id_value":"l87",
                            "id_type":"string"
                        }
                    ],
                    "modification":[
                        {
                            "modification_key":"DISABLED",
                            "modification_value":false,
                            "modification_type":"boolean"
                        }
                    ]
                },
                {
                    "component_type":"gov.lanl.micot.infrastructure.ep.model.LineImpl",
                    "id":[
                        {
                            "id_key":"OPENDSS_LEGACY_ID",
                            "id_value":"l88",
                            "id_type":"string"
                        }
                    ],
                    "modification":[
                        {
                            "modification_key":"DISABLED",
                            "modification_value":false,
                            "modification_type":"boolean"
                        }
                    ]
                },
                {
                    "component_type":"gov.lanl.micot.infrastructure.ep.model.LineImpl",
                    "id":[
                        {
                            "id_key":"OPENDSS_LEGACY_ID",
                            "id_value":"l89",
                            "id_type":"string"
                        }
                    ],
                    "modification":[
                        {
                            "modification_key":"DISABLED",
                            "modification_value":false,
                            "modification_type":"boolean"
                        }
                    ]
                },
                {
                    "component_type":"gov.lanl.micot.infrastructure.ep.model.LineImpl",
                    "id":[
                        {
                            "id_key":"OPENDSS_LEGACY_ID",
                            "id_value":"l90",
                            "id_type":"string"
                        }
                    ],
                    "modification":[
                        {
                            "modification_key":"DISABLED",
                            "modification_value":false,
                            "modification_type":"boolean"
                        }
                    ]
                },
                {
                    "component_type":"gov.lanl.micot.infrastructure.ep.model.LineImpl",
                    "id":[
                        {
                            "id_key":"OPENDSS_LEGACY_ID",
                            "id_value":"l91",
                            "id_type":"string"
                        }
                    ],
                    "modification":[
                        {
                            "modification_key":"DISABLED",
                            "modification_value":false,
                            "modification_type":"boolean"
                        }
                    ]
                },
                {
                    "component_type":"gov.lanl.micot.infrastructure.ep.model.LineImpl",
                    "id":[
                        {
                            "id_key":"OPENDSS_LEGACY_ID",
                            "id_value":"l92",
                            "id_type":"string"
                        }
                    ],
                    "modification":[
                        {
                            "modification_key":"DISABLED",
                            "modification_value":false,
                            "modification_type":"boolean"
                        }
                    ]
                },
                {
                    "component_type":"gov.lanl.micot.infrastructure.ep.model.LineImpl",
                    "id":[
                        {
                            "id_key":"OPENDSS_LEGACY_ID",
                            "id_value":"l93",
                            "id_type":"string"
                        }
                    ],
                    "modification":[
                        {
                            "modification_key":"DISABLED",
                            "modification_value":false,
                            "modification_type":"boolean"
                        }
                    ]
                },
                {
                    "component_type":"gov.lanl.micot.infrastructure.ep.model.LineImpl",
                    "id":[
                        {
                            "id_key":"OPENDSS_LEGACY_ID",
                            "id_value":"l94",
                            "id_type":"string"
                        }
                    ],
                    "modification":[
                        {
                            "modification_key":"DISABLED",
                            "modification_value":false,
                            "modification_type":"boolean"
                        }
                    ]
                },
                {
                    "component_type":"gov.lanl.micot.infrastructure.ep.model.LineImpl",
                    "id":[
                        {
                            "id_key":"OPENDSS_LEGACY_ID",
                            "id_value":"l95",
                            "id_type":"string"
                        }
                    ],
                    "modification":[
                        {
                            "modification_key":"DISABLED",
                            "modification_value":false,
                            "modification_type":"boolean"
                        }
                    ]
                },
                {
                    "component_type":"gov.lanl.micot.infrastructure.ep.model.LineImpl",
                    "id":[
                        {
                            "id_key":"OPENDSS_LEGACY_ID",
                            "id_value":"l96",
                            "id_type":"string"
                        }
                    ],
                    "modification":[
                        {
                            "modification_key":"DISABLED",
                            "modification_value":false,
                            "modification_type":"boolean"
                        }
                    ]
                },
                {
                    "component_type":"gov.lanl.micot.infrastructure.ep.model.LineImpl",
                    "id":[
                        {
                            "id_key":"OPENDSS_LEGACY_ID",
                            "id_value":"l97",
                            "id_type":"string"
                        }
                    ],
                    "modification":[
                        {
                            "modification_key":"DISABLED",
                            "modification_value":false,
                            "modification_type":"boolean"
                        }
                    ]
                },
                {
                    "component_type":"gov.lanl.micot.infrastructure.ep.model.LineImpl",
                    "id":[
                        {
                            "id_key":"OPENDSS_LEGACY_ID",
                            "id_value":"l98",
                            "id_type":"string"
                        }
                    ],
                    "modification":[
                        {
                            "modification_key":"DISABLED",
                            "modification_value":false,
                            "modification_type":"boolean"
                        }
                    ]
                },
                {
                    "component_type":"gov.lanl.micot.infrastructure.ep.model.LineImpl",
                    "id":[
                        {
                            "id_key":"OPENDSS_LEGACY_ID",
                            "id_value":"l99",
                            "id_type":"string"
                        }
                    ],
                    "modification":[
                        {
                            "modification_key":"DISABLED",
                            "modification_value":false,
                            "modification_type":"boolean"
                        }
                    ]
                },
                {
                    "component_type":"gov.lanl.micot.infrastructure.ep.model.LineImpl",
                    "id":[
                        {
                            "id_key":"OPENDSS_LEGACY_ID",
                            "id_value":"l118",
                            "id_type":"string"
                        }
                    ],
                    "modification":[
                        {
                            "modification_key":"DISABLED",
                            "modification_value":false,
                            "modification_type":"boolean"
                        }
                    ]
                },
                {
                    "component_type":"gov.lanl.micot.infrastructure.ep.model.LineImpl",
                    "id":[
                        {
                            "id_key":"OPENDSS_LEGACY_ID",
                            "id_value":"l100",
                            "id_type":"string"
                        }
                    ],
                    "modification":[
                        {
                            "modification_key":"DISABLED",
                            "modification_value":false,
                            "modification_type":"boolean"
                        }
                    ]
                },
                {
                    "component_type":"gov.lanl.micot.infrastructure.ep.model.LineImpl",
                    "id":[
                        {
                            "id_key":"OPENDSS_LEGACY_ID",
                            "id_value":"l101",
                            "id_type":"string"
                        }
                    ],
                    "modification":[
                        {
                            "modification_key":"DISABLED",
                            "modification_value":false,
                            "modification_type":"boolean"
                        }
                    ]
                },
                {
                    "component_type":"gov.lanl.micot.infrastructure.ep.model.LineImpl",
                    "id":[
                        {
                            "id_key":"OPENDSS_LEGACY_ID",
                            "id_value":"l102",
                            "id_type":"string"
                        }
                    ],
                    "modification":[
                        {
                            "modification_key":"DISABLED",
                            "modification_value":false,
                            "modification_type":"boolean"
                        }
                    ]
                },
                {
                    "component_type":"gov.lanl.micot.infrastructure.ep.model.LineImpl",
                    "id":[
                        {
                            "id_key":"OPENDSS_LEGACY_ID",
                            "id_value":"l103",
                            "id_type":"string"
                        }
                    ],
                    "modification":[
                        {
                            "modification_key":"DISABLED",
                            "modification_value":false,
                            "modification_type":"boolean"
                        }
                    ]
                },
                {
                    "component_type":"gov.lanl.micot.infrastructure.ep.model.LineImpl",
                    "id":[
                        {
                            "id_key":"OPENDSS_LEGACY_ID",
                            "id_value":"l104",
                            "id_type":"string"
                        }
                    ],
                    "modification":[
                        {
                            "modification_key":"DISABLED",
                            "modification_value":false,
                            "modification_type":"boolean"
                        }
                    ]
                },
                {
                    "component_type":"gov.lanl.micot.infrastructure.ep.model.LineImpl",
                    "id":[
                        {
                            "id_key":"OPENDSS_LEGACY_ID",
                            "id_value":"l105",
                            "id_type":"string"
                        }
                    ],
                    "modification":[
                        {
                            "modification_key":"DISABLED",
                            "modification_value":false,
                            "modification_type":"boolean"
                        }
                    ]
                },
                {
                    "component_type":"gov.lanl.micot.infrastructure.ep.model.LineImpl",
                    "id":[
                        {
                            "id_key":"OPENDSS_LEGACY_ID",
                            "id_value":"l106",
                            "id_type":"string"
                        }
                    ],
                    "modification":[
                        {
                            "modification_key":"DISABLED",
                            "modification_value":false,
                            "modification_type":"boolean"
                        }
                    ]
                },
                {
                    "component_type":"gov.lanl.micot.infrastructure.ep.model.LineImpl",
                    "id":[
                        {
                            "id_key":"OPENDSS_LEGACY_ID",
                            "id_value":"l107",
                            "id_type":"string"
                        }
                    ],
                    "modification":[
                        {
                            "modification_key":"DISABLED",
                            "modification_value":false,
                            "modification_type":"boolean"
                        }
                    ]
                },
                {
                    "component_type":"gov.lanl.micot.infrastructure.ep.model.LineImpl",
                    "id":[
                        {
                            "id_key":"OPENDSS_LEGACY_ID",
                            "id_value":"l108",
                            "id_type":"string"
                        }
                    ],
                    "modification":[
                        {
                            "modification_key":"DISABLED",
                            "modification_value":false,
                            "modification_type":"boolean"
                        }
                    ]
                },
                {
                    "component_type":"gov.lanl.micot.infrastructure.ep.model.LineImpl",
                    "id":[
                        {
                            "id_key":"OPENDSS_LEGACY_ID",
                            "id_value":"l109",
                            "id_type":"string"
                        }
                    ],
                    "modification":[
                        {
                            "modification_key":"DISABLED",
                            "modification_value":false,
                            "modification_type":"boolean"
                        }
                    ]
                },
                {
                    "component_type":"gov.lanl.micot.infrastructure.ep.model.LineImpl",
                    "id":[
                        {
                            "id_key":"OPENDSS_LEGACY_ID",
                            "id_value":"l110",
                            "id_type":"string"
                        }
                    ],
                    "modification":[
                        {
                            "modification_key":"DISABLED",
                            "modification_value":false,
                            "modification_type":"boolean"
                        }
                    ]
                },
                {
                    "component_type":"gov.lanl.micot.infrastructure.ep.model.LineImpl",
                    "id":[
                        {
                            "id_key":"OPENDSS_LEGACY_ID",
                            "id_value":"l111",
                            "id_type":"string"
                        }
                    ],
                    "modification":[
                        {
                            "modification_key":"DISABLED",
                            "modification_value":false,
                            "modification_type":"boolean"
                        }
                    ]
                },
                {
                    "component_type":"gov.lanl.micot.infrastructure.ep.model.LineImpl",
                    "id":[
                        {
                            "id_key":"OPENDSS_LEGACY_ID",
                            "id_value":"l112",
                            "id_type":"string"
                        }
                    ],
                    "modification":[
                        {
                            "modification_key":"DISABLED",
                            "modification_value":false,
                            "modification_type":"boolean"
                        }
                    ]
                },
                {
                    "component_type":"gov.lanl.micot.infrastructure.ep.model.LineImpl",
                    "id":[
                        {
                            "id_key":"OPENDSS_LEGACY_ID",
                            "id_value":"l113",
                            "id_type":"string"
                        }
                    ],
                    "modification":[
                        {
                            "modification_key":"DISABLED",
                            "modification_value":false,
                            "modification_type":"boolean"
                        }
                    ]
                },
                {
                    "component_type":"gov.lanl.micot.infrastructure.ep.model.LineImpl",
                    "id":[
                        {
                            "id_key":"OPENDSS_LEGACY_ID",
                            "id_value":"l114",
                            "id_type":"string"
                        }
                    ],
                    "modification":[
                        {
                            "modification_key":"DISABLED",
                            "modification_value":false,
                            "modification_type":"boolean"
                        }
                    ]
                },
                {
                    "component_type":"gov.lanl.micot.infrastructure.ep.model.LineImpl",
                    "id":[
                        {
                            "id_key":"OPENDSS_LEGACY_ID",
                            "id_value":"l116",
                            "id_type":"string"
                        }
                    ],
                    "modification":[
                        {
                            "modification_key":"DISABLED",
                            "modification_value":false,
                            "modification_type":"boolean"
                        }
                    ]
                },
                {
                    "component_type":"gov.lanl.micot.infrastructure.ep.model.LineImpl",
                    "id":[
                        {
                            "id_key":"OPENDSS_LEGACY_ID",
                            "id_value":"l117",
                            "id_type":"string"
                        }
                    ],
                    "modification":[
                        {
                            "modification_key":"DISABLED",
                            "modification_value":false,
                            "modification_type":"boolean"
                        }
                    ]
                }
            ]
        }
    ]
}